{
  "metadata": {
    "description": "Enhanced profiling analysis results with processor-specific TDP calculations",
    "source_file": "/Users/arriazui/Desktop/GreenComputing/flexecutor-main/examples/general_usage/plot_generation/../../ml/profiling/ml/stage1.json",
    "title": "ml_stage1",
    "example": "ml",
    "stage": "stage1",
    "memory": "unknown",
    "platform": "unknown",
    "architecture": "unknown",
    "total_configurations": 5,
    "aws_x86_processors": {
      "AMD EPYC": {
        "tdp_watts": 225,
        "description": "AMD EPYC processor for AWS x86 instances"
      },
      "Intel(R) Xeon(R) Processor @ 2.90GHz": {
        "tdp_watts": 300,
        "description": "Intel Xeon processor @ 2.90GHz for AWS x86 instances"
      }
    },
    "processor_info": null
  },
  "analysis_results": [
    {
      "cpu": 4,
      "memory": 2048,
      "workers": 1,
      "total_executions": 1,
      "avg_read": 0.34912538528442383,
      "avg_compute": 22.921571016311646,
      "avg_write": 0.52866530418396,
      "avg_cold_start": 1.1521389484405518,
      "avg_worker_time_execution": 26.489872932434082,
      "avg_rapl": 12.0,
      "avg_tdp": 1415.8837082386017,
      "avg_execution": 23.79936170578003,
      "avg_psutil_cpu_percent": 1.9,
      "min_compute": 22.921571016311646,
      "max_compute": 22.921571016311646,
      "total_compute": 22.921571016311646,
      "min_rapl": 12,
      "max_rapl": 12,
      "total_rapl": 12.0,
      "min_tdp": 1415.8837082386017,
      "max_tdp": 1415.8837082386017,
      "total_tdp": 1415.8837082386017,
      "min_execution": 0.34912538528442383,
      "max_execution": 22.921571016311646,
      "total_execution": 23.79936170578003,
      "avg_time_consumption": 26.48987293,
      "min_time_consumption": 26.48987293,
      "max_time_consumption": 26.48987293,
      "total_time_consumption": 26.48987293,
      "avg_perf_energy_cores": 0.0,
      "min_perf_energy_cores": 0.0,
      "max_perf_energy_cores": 0.0,
      "total_perf_energy_cores": 0.0,
      "avg_rapl_energy_cores": 0.0,
      "min_rapl_energy_cores": 0.0,
      "max_rapl_energy_cores": 0.0,
      "total_rapl_energy_cores": 0.0,
      "avg_ebpf_energy_pkg": 0.0,
      "min_ebpf_energy_pkg": 0.0,
      "max_ebpf_energy_pkg": 0.0,
      "total_ebpf_energy_pkg": 0.0,
      "avg_ebpf_energy_cores": 0.0,
      "min_ebpf_energy_cores": 0.0,
      "max_ebpf_energy_cores": 0.0,
      "total_ebpf_energy_cores": 0.0,
      "cpu_architecture": "aarch64",
      "cpu_cores_logical": 2,
      "aws_cpu_type": "type:lambda-function|arch:aarch64|lambda:True|mem:2048",
      "cost_aws_moneywise": 0.6115475147151946,
      "processor_tdp_watts": 100,
      "processor_type": "type:lambda-function|arch:aarch64|lambda:True|mem:2048"
    },
    {
      "cpu": 4,
      "memory": 2048,
      "workers": 4,
      "total_executions": 1,
      "avg_read": 0.3495582938194275,
      "avg_compute": 23.6725435256958,
      "avg_write": 0.5803524851799011,
      "avg_cold_start": 1.233727216720581,
      "avg_worker_time_execution": 27.44970679283142,
      "avg_rapl": 12.0,
      "avg_tdp": 1462.7510569274425,
      "avg_execution": 24.60245430469513,
      "avg_psutil_cpu_percent": 3.375,
      "min_compute": 23.23361849784851,
      "max_compute": 24.387850284576416,
      "total_compute": 94.6901741027832,
      "min_rapl": 12,
      "max_rapl": 12,
      "total_rapl": 48.0,
      "min_tdp": 1437.3434784412386,
      "max_tdp": 1502.9272284269337,
      "total_tdp": 5851.00422770977,
      "min_execution": 0.3495582938194275,
      "max_execution": 23.6725435256958,
      "total_execution": 98.40981721878052,
      "avg_time_consumption": 27.449706792500002,
      "min_time_consumption": 27.0344789,
      "max_time_consumption": 28.01355505,
      "total_time_consumption": 109.79882717000001,
      "avg_perf_energy_cores": 0.0,
      "min_perf_energy_cores": 0.0,
      "max_perf_energy_cores": 0.0,
      "total_perf_energy_cores": 0.0,
      "avg_rapl_energy_cores": 0.0,
      "min_rapl_energy_cores": 0.0,
      "max_rapl_energy_cores": 0.0,
      "total_rapl_energy_cores": 0.0,
      "avg_ebpf_energy_pkg": 0.0,
      "min_ebpf_energy_pkg": 0.0,
      "max_ebpf_energy_pkg": 0.0,
      "total_ebpf_energy_pkg": 0.0,
      "avg_ebpf_energy_cores": 0.0,
      "min_ebpf_energy_cores": 0.0,
      "max_ebpf_energy_cores": 0.0,
      "total_ebpf_energy_cores": 0.0,
      "cpu_architecture": "aarch64",
      "cpu_cores_logical": 2,
      "aws_cpu_type": "type:lambda-function|arch:aarch64|lambda:True|mem:2048",
      "cost_aws_moneywise": 2.526333845062256,
      "processor_tdp_watts": 100,
      "processor_type": "type:lambda-function|arch:aarch64|lambda:True|mem:2048"
    },
    {
      "cpu": 4,
      "memory": 2048,
      "workers": 5,
      "total_executions": 2,
      "avg_read": 0.32025115489959716,
      "avg_compute": 22.999669098854064,
      "avg_write": 0.6080557584762574,
      "avg_cold_start": 1.213974905014038,
      "avg_worker_time_execution": 26.68650403022766,
      "avg_rapl": 12.0,
      "avg_tdp": 1424.8678031384945,
      "avg_execution": 23.92797601222992,
      "avg_psutil_cpu_percent": 2.52,
      "min_compute": 22.44696354866028,
      "max_compute": 23.691269397735596,
      "total_compute": 114.99834549427032,
      "min_rapl": 12,
      "max_rapl": 12,
      "total_rapl": 60.0,
      "min_tdp": 1392.2755472183228,
      "max_tdp": 1469.2397910118102,
      "total_tdp": 7124.3390156924725,
      "min_execution": 0.32025115489959716,
      "max_execution": 22.999669098854064,
      "total_execution": 119.6398800611496,
      "avg_time_consumption": 26.68650403,
      "min_time_consumption": 25.97529006,
      "max_time_consumption": 27.6172893,
      "total_time_consumption": 133.43252015,
      "avg_perf_energy_cores": 0.0,
      "min_perf_energy_cores": 0.0,
      "max_perf_energy_cores": 0.0,
      "total_perf_energy_cores": 0.0,
      "avg_rapl_energy_cores": 0.0,
      "min_rapl_energy_cores": 0.0,
      "max_rapl_energy_cores": 0.0,
      "total_rapl_energy_cores": 0.0,
      "avg_ebpf_energy_pkg": 0.0,
      "min_ebpf_energy_pkg": 0.0,
      "max_ebpf_energy_pkg": 0.0,
      "total_ebpf_energy_pkg": 0.0,
      "avg_ebpf_energy_cores": 0.0,
      "min_ebpf_energy_cores": 0.0,
      "max_ebpf_energy_cores": 0.0,
      "total_ebpf_energy_cores": 0.0,
      "cpu_architecture": "aarch64",
      "cpu_cores_logical": 2,
      "aws_cpu_type": "type:lambda-function|arch:aarch64|lambda:True|mem:2048",
      "cost_aws_moneywise": 3.068155857787132,
      "processor_tdp_watts": 100,
      "processor_type": "type:lambda-function|arch:aarch64|lambda:True|mem:2048"
    },
    {
      "cpu": 4,
      "memory": 2048,
      "workers": 6,
      "total_executions": 3,
      "avg_read": 0.35121432940165204,
      "avg_compute": 23.358205795288086,
      "avg_write": 0.590413769086202,
      "avg_cold_start": 1.2499880525800917,
      "avg_worker_time_execution": 27.0273603465822,
      "avg_rapl": 12.0,
      "avg_tdp": 1446.9728029919995,
      "avg_execution": 24.29983389377594,
      "avg_psutil_cpu_percent": 2.7888888888888888,
      "min_compute": 22.44852352142334,
      "max_compute": 25.626986265182495,
      "total_compute": 140.14923477172852,
      "min_rapl": 12,
      "max_rapl": 12,
      "total_rapl": 72.0,
      "min_tdp": 1399.0821132659914,
      "max_tdp": 1567.2224290966988,
      "total_tdp": 8681.836817951997,
      "min_execution": 0.35121432940165204,
      "max_execution": 23.358205795288086,
      "total_execution": 145.79900336265564,
      "avg_time_consumption": 27.02736034611111,
      "min_time_consumption": 26.10227823,
      "max_time_consumption": 29.10348058,
      "total_time_consumption": 162.16416207666666,
      "avg_perf_energy_cores": 0.0,
      "min_perf_energy_cores": 0.0,
      "max_perf_energy_cores": 0.0,
      "total_perf_energy_cores": 0.0,
      "avg_rapl_energy_cores": 0.0,
      "min_rapl_energy_cores": 0.0,
      "max_rapl_energy_cores": 0.0,
      "total_rapl_energy_cores": 0.0,
      "avg_ebpf_energy_pkg": 0.0,
      "min_ebpf_energy_pkg": 0.0,
      "max_ebpf_energy_pkg": 0.0,
      "total_ebpf_energy_pkg": 0.0,
      "avg_ebpf_energy_cores": 0.0,
      "min_ebpf_energy_cores": 0.0,
      "max_ebpf_energy_cores": 0.0,
      "total_ebpf_energy_cores": 0.0,
      "cpu_architecture": "aarch64",
      "cpu_cores_logical": 2,
      "aws_cpu_type": "type:lambda-function|arch:aarch64|lambda:True|mem:2048",
      "cost_aws_moneywise": 3.739181583709717,
      "processor_tdp_watts": 100,
      "processor_type": "type:lambda-function|arch:aarch64|lambda:True|mem:2048"
    },
    {
      "cpu": 4,
      "memory": 2048,
      "workers": 7,
      "total_executions": 3,
      "avg_read": 0.3306925069718134,
      "avg_compute": 22.956958169028873,
      "avg_write": 0.5642007419041225,
      "avg_cold_start": 1.954940432593936,
      "avg_worker_time_execution": 26.877170676276798,
      "avg_rapl": 12.0,
      "avg_tdp": 1430.6408997189433,
      "avg_execution": 23.85185141790481,
      "avg_psutil_cpu_percent": 2.480952380952381,
      "min_compute": 21.528006076812744,
      "max_compute": 23.561777353286743,
      "total_compute": 160.69870718320212,
      "min_rapl": 12,
      "max_rapl": 12,
      "total_rapl": 84.0,
      "min_tdp": 1349.7259952545166,
      "max_tdp": 1467.458185136318,
      "total_tdp": 10014.486298032603,
      "min_execution": 0.3306925069718134,
      "max_execution": 22.956958169028873,
      "total_execution": 166.96295992533368,
      "avg_time_consumption": 26.877170676190477,
      "min_time_consumption": 25.56299233,
      "max_time_consumption": 27.5829556,
      "total_time_consumption": 188.14019473333335,
      "avg_perf_energy_cores": 0.0,
      "min_perf_energy_cores": 0.0,
      "max_perf_energy_cores": 0.0,
      "total_perf_energy_cores": 0.0,
      "avg_rapl_energy_cores": 0.0,
      "min_rapl_energy_cores": 0.0,
      "max_rapl_energy_cores": 0.0,
      "total_rapl_energy_cores": 0.0,
      "avg_ebpf_energy_pkg": 0.0,
      "min_ebpf_energy_pkg": 0.0,
      "max_ebpf_energy_pkg": 0.0,
      "total_ebpf_energy_pkg": 0.0,
      "avg_ebpf_energy_cores": 0.0,
      "min_ebpf_energy_cores": 0.0,
      "max_ebpf_energy_cores": 0.0,
      "total_ebpf_energy_cores": 0.0,
      "cpu_architecture": "aarch64",
      "cpu_cores_logical": 2,
      "aws_cpu_type": "type:lambda-function|arch:aarch64|lambda:True|mem:2048",
      "cost_aws_moneywise": 4.2874415076478325,
      "processor_tdp_watts": 100,
      "processor_type": "type:lambda-function|arch:aarch64|lambda:True|mem:2048"
    }
  ]
}